covid19_us/__init__.py
covid19_us/download.py
covid19_us/asset/cities_to_fips.pkl
covid19_us/asset/fips_and_zip.txt
covid19_us/asset/us_state_abbrev.json
covid19_us/asset/zips_to_fips.pkl
covid19_us-1.0.3.dist-info/AUTHORS.rst
covid19_us-1.0.3.dist-info/LICENSE
covid19_us-1.0.3.dist-info/METADATA
covid19_us-1.0.3.dist-info/WHEEL
covid19_us-1.0.3.dist-info/top_level.txt
covid19_us-1.0.3.dist-info/RECORD
