Metadata-Version: 2.1
Name: covid19-us
Version: 1.0.3
Summary: this package provides a streamlined way to download covid data by state
Home-page: https://github.com/HaigangLiu/covid19-us
Author: Haigang Liu
Author-email: haigang@email.sc.edu
License: MIT license
Keywords: covid19_us
Platform: UNKNOWN
Classifier: Development Status :: 2 - Pre-Alpha
Classifier: Intended Audience :: Developers
Classifier: License :: OSI Approved :: MIT License
Classifier: Natural Language :: English
Classifier: Programming Language :: Python :: 3
Classifier: Programming Language :: Python :: 3.5
Classifier: Programming Language :: Python :: 3.6
Classifier: Programming Language :: Python :: 3.7
Classifier: Programming Language :: Python :: 3.8
Requires-Python: >=3.6
License-File: LICENSE
License-File: AUTHORS.rst
